Workbook

Sheet Executive Dashboard
B2: AI Customer Support Ticket Intelligence Dashboard
B5: TOTAL TICKETS | D5: AVG RESOLUTION TIME (HRS) | F5: HIGH PRIORITY TICKETS | H5: OPEN TICKETS | J5: CLOSED TICKETS | L5: AVERAGE CSAT RATING
B6: =COUNTA('Cleaned Data'!A2:A8470) -> 8469 | D6: =ROUND(AVERAGE('Cleaned Data'!X2:X8470), 2) -> 61.01 | F6: =COUNTIF('Cleaned Data'!M2:M8470, "High") -> 2085 | H6: =COUNTIF('Cleaned Data'!K2:K8470, "Open") -> 2819 | J6: =COUNTIF('Cleaned Data'!K2:K8470, "Closed") -> 2769 | L6: =ROUND(AVERAGEIFS('Cleaned Data'!Q2:Q8470, 'Cleaned Data'!Q2:Q8470, ">=1"), 2) -> 2.99
B9: Ticket Distribution by Category & Priority
B10: Ticket Category | C10: High | D10: Medium | E10: Low | F10: Total
B11: Account | C11: =COUNTIFS('Cleaned Data'!$T$2:$T$8470, B11, 'Cleaned Data'!$M$2:$M$8470, "High") -> 46 | D11: =COUNTIFS('Cleaned Data'!$T$2:$T$8470, B11, 'Cleaned Data'!$M$2:$M$8470, "Medium") -> 52 | E11: =COUNTIFS('Cleaned Data'!$T$2:$T$8470, B11, 'Cleaned Data'!$M$2:$M$8470, "Low") -> 43 | F11: =SUM(C11:E11) -> 141
B12: Billing | C12: =COUNTIFS('Cleaned Data'!$T$2:$T$8470, B12, 'Cleaned Data'!$M$2:$M$8470, "High") -> 274 | D12: =COUNTIFS('Cleaned Data'!$T$2:$T$8470, B12, 'Cleaned Data'!$M$2:$M$8470, "Medium") -> 315 | E12: =COUNTIFS('Cleaned Data'!$T$2:$T$8470, B12, 'Cleaned Data'!$M$2:$M$8470, "Low") -> 292 | F12: =SUM(C12:E12) -> 881
B13: Login | C13: =COUNTIFS('Cleaned Data'!$T$2:$T$8470, B13, 'Cleaned Data'!$M$2:$M$8470, "High") -> 262 | D13: =COUNTIFS('Cleaned Data'!$T$2:$T$8470, B13, 'Cleaned Data'!$M$2:$M$8470, "Medium") -> 281 | E13: =COUNTIFS('Cleaned Data'!$T$2:$T$8470, B13, 'Cleaned Data'!$M$2:$M$8470, "Low") -> 270 | F13: =SUM(C13:E13) -> 813
B14: Refund | C14: =COUNTIFS('Cleaned Data'!$T$2:$T$8470, B14, 'Cleaned Data'!$M$2:$M$8470, "High") -> 168 | D14: =COUNTIFS('Cleaned Data'!$T$2:$T$8470, B14, 'Cleaned Data'!$M$2:$M$8470, "Medium") -> 179 | E14: =COUNTIFS('Cleaned Data'!$T$2:$T$8470, B14, 'Cleaned Data'!$M$2:$M$8470, "Low") -> 176 | F14: =SUM(C14:E14) -> 523
B15: Shipping | C15: =COUNTIFS('Cleaned Data'!$T$2:$T$8470, B15, 'Cleaned Data'!$M$2:$M$8470, "High") -> 267 | D15: =COUNTIFS('Cleaned Data'!$T$2:$T$8470, B15, 'Cleaned Data'!$M$2:$M$8470, "Medium") -> 267 | E15: =COUNTIFS('Cleaned Data'!$T$2:$T$8470, B15, 'Cleaned Data'!$M$2:$M$8470, "Low") -> 222 | F15: =SUM(C15:E15) -> 756
B16: Technical | C16: =COUNTIFS('Cleaned Data'!$T$2:$T$8470, B16, 'Cleaned Data'!$M$2:$M$8470, "High") -> 1068 | D16: =COUNTIFS('Cleaned Data'!$T$2:$T$8470, B16, 'Cleaned Data'!$M$2:$M$8470, "Medium") -> 1098 | E16: =COUNTIFS('Cleaned Data'!$T$2:$T$8470, B16, 'Cleaned Data'!$M$2:$M$8470, "Low") -> 1060 | F16: =SUM(C16:E16) -> 3226
B17: Total | C17: =SUM(C11:C16) -> 2085 | D17: =SUM(D11:D16) -> 2192 | E17: =SUM(E11:E16) -> 2063 | F17: =SUM(F11:F16) -> 6340
B19: Top 10 Support Agents Performance
B20: Support Agent | C20: Tickets Assigned | D20: Average CSAT | E20: Avg Resolution Time (hrs)
B21: Kevin Bacon | C21: =COUNTIF('Cleaned Data'!$U$2:$U$8470, B21) -> 623 | D21: =ROUND(AVERAGEIFS('Cleaned Data'!$Q$2:$Q$8470, 'Cleaned Data'!$U$2:$U$8470, B21, 'Cleaned Data'!$Q$2:$Q$8470, ">=1"), 2) -> 2.82 | E21: =ROUND(AVERAGEIF('Cleaned Data'!$U$2:$U$8470, B21, 'Cleaned Data'!$X$2:$X$8470), 2) -> 62.14
B22: Michael Scott | C22: =COUNTIF('Cleaned Data'!$U$2:$U$8470, B22) -> 586 | D22: =ROUND(AVERAGEIFS('Cleaned Data'!$Q$2:$Q$8470, 'Cleaned Data'!$U$2:$U$8470, B22, 'Cleaned Data'!$Q$2:$Q$8470, ">=1"), 2) -> 2.98 | E22: =ROUND(AVERAGEIF('Cleaned Data'!$U$2:$U$8470, B22, 'Cleaned Data'!$X$2:$X$8470), 2) -> 61.09
B23: Ian Malcolm | C23: =COUNTIF('Cleaned Data'!$U$2:$U$8470, B23) -> 582 | D23: =ROUND(AVERAGEIFS('Cleaned Data'!$Q$2:$Q$8470, 'Cleaned Data'!$U$2:$U$8470, B23, 'Cleaned Data'!$Q$2:$Q$8470, ">=1"), 2) -> 2.8 | E23: =ROUND(AVERAGEIF('Cleaned Data'!$U$2:$U$8470, B23, 'Cleaned Data'!$X$2:$X$8470), 2) -> 60.14
B24: Bob Johnson | C24: =COUNTIF('Cleaned Data'!$U$2:$U$8470, B24) -> 577 | D24: =ROUND(AVERAGEIFS('Cleaned Data'!$Q$2:$Q$8470, 'Cleaned Data'!$U$2:$U$8470, B24, 'Cleaned Data'!$Q$2:$Q$8470, ">=1"), 2) -> 3.1 | E24: =ROUND(AVERAGEIF('Cleaned Data'!$U$2:$U$8470, B24, 'Cleaned Data'!$X$2:$X$8470), 2) -> 64.92
B25: Hannah Abbott | C25: =COUNTIF('Cleaned Data'!$U$2:$U$8470, B25) -> 577 | D25: =ROUND(AVERAGEIFS('Cleaned Data'!$Q$2:$Q$8470, 'Cleaned Data'!$U$2:$U$8470, B25, 'Cleaned Data'!$Q$2:$Q$8470, ">=1"), 2) -> 3.11 | E25: =ROUND(AVERAGEIF('Cleaned Data'!$U$2:$U$8470, B25, 'Cleaned Data'!$X$2:$X$8470), 2) -> 63.71
B26: Laura Croft | C26: =COUNTIF('Cleaned Data'!$U$2:$U$8470, B26) -> 576 | D26: =ROUND(AVERAGEIFS('Cleaned Data'!$Q$2:$Q$8470, 'Cleaned Data'!$U$2:$U$8470, B26, 'Cleaned Data'!$Q$2:$Q$8470, ">=1"), 2) -> 2.84 | E26: =ROUND(AVERAGEIF('Cleaned Data'!$U$2:$U$8470, B26, 'Cleaned Data'!$X$2:$X$8470), 2) -> 61.96
B27: George Clark | C27: =COUNTIF('Cleaned Data'!$U$2:$U$8470, B27) -> 567 | D27: =ROUND(AVERAGEIFS('Cleaned Data'!$Q$2:$Q$8470, 'Cleaned Data'!$U$2:$U$8470, B27, 'Cleaned Data'!$Q$2:$Q$8470, ">=1"), 2) -> 2.94 | E27: =ROUND(AVERAGEIF('Cleaned Data'!$U$2:$U$8470, B27, 'Cleaned Data'!$X$2:$X$8470), 2) -> 57.27
B28: Fiona Gallagher | C28: =COUNTIF('Cleaned Data'!$U$2:$U$8470, B28) -> 567 | D28: =ROUND(AVERAGEIFS('Cleaned Data'!$Q$2:$Q$8470, 'Cleaned Data'!$U$2:$U$8470, B28, 'Cleaned Data'!$Q$2:$Q$8470, ">=1"), 2) -> 3.08 | E28: =ROUND(AVERAGEIF('Cleaned Data'!$U$2:$U$8470, B28, 'Cleaned Data'!$X$2:$X$8470), 2) -> 60.99
B29: Ethan Hunt | C29: =COUNTIF('Cleaned Data'!$U$2:$U$8470, B29) -> 565 | D29: =ROUND(AVERAGEIFS('Cleaned Data'!$Q$2:$Q$8470, 'Cleaned Data'!$U$2:$U$8470, B29, 'Cleaned Data'!$Q$2:$Q$8470, ">=1"), 2) -> 3.1 | E29: =ROUND(AVERAGEIF('Cleaned Data'!$U$2:$U$8470, B29, 'Cleaned Data'!$X$2:$X$8470), 2) -> 59.34
B30: Charlie Brown | C30: =COUNTIF('Cleaned Data'!$U$2:$U$8470, B30) -> 563 | D30: =ROUND(AVERAGEIFS('Cleaned Data'!$Q$2:$Q$8470, 'Cleaned Data'!$U$2:$U$8470, B30, 'Cleaned Data'!$Q$2:$Q$8470, ">=1"), 2) -> 3.04 | E30: =ROUND(AVERAGEIF('Cleaned Data'!$U$2:$U$8470, B30, 'Cleaned Data'!$X$2:$X$8470), 2) -> 59.09
B33: Monthly Ticket Volume Trends
B34: Month | C34: Tickets Logged
B35: 2021-12 | C35: =COUNTIF('Cleaned Data'!$Y$2:$Y$8470, B35) -> 3
B36: 2022-01 | C36: =COUNTIF('Cleaned Data'!$Y$2:$Y$8470, B36) -> 230
B37: 2022-02 | C37: =COUNTIF('Cleaned Data'!$Y$2:$Y$8470, B37) -> 232
B38: 2022-03 | C38: =COUNTIF('Cleaned Data'!$Y$2:$Y$8470, B38) -> 273
B39: 2022-04 | C39: =COUNTIF('Cleaned Data'!$Y$2:$Y$8470, B39) -> 229
B40: 2022-05 | C40: =COUNTIF('Cleaned Data'!$Y$2:$Y$8470, B40) -> 254
B41: 2022-06 | C41: =COUNTIF('Cleaned Data'!$Y$2:$Y$8470, B41) -> 231
B42: 2022-07 | C42: =COUNTIF('Cleaned Data'!$Y$2:$Y$8470, B42) -> 241
B43: 2022-08 | C43: =COUNTIF('Cleaned Data'!$Y$2:$Y$8470, B43) -> 240
B44: 2022-09 | C44: =COUNTIF('Cleaned Data'!$Y$2:$Y$8470, B44) -> 239
B45: 2022-10 | C45: =COUNTIF('Cleaned Data'!$Y$2:$Y$8470, B45) -> 246
B46: 2022-11 | C46: =COUNTIF('Cleaned Data'!$Y$2:$Y$8470, B46) -> 228
... B71: 2024-12 | C71: =COUNTIF('Cleaned Data'!$Y$2:$Y$8470, B71) -> 212

Sheet Cleaned Data
A1: Ticket_ID | B1: Customer_Name | C1: Customer_Email | D1: Customer_Age | E1: Customer_Gender | F1: Product_Purchased | G1: Date_of_Purchase | H1: Ticket_Type | I1: Ticket_Subject | J1: Ticket_Description | K1: Ticket_Status | L1: Resolution | M1: Ticket_Priority | N1: Ticket_Channel | O1: First_Response_Time | P1: Time_to_Resolution | Q1: Customer_Satisfaction_Rating | R1: Priority | S1: Status | T1: Ticket_Category | U1: Support_Agent | V1: Created_Date | W1: Resolved_Date | X1: Resolution_Time | Y1: Year_Month
A2: 1 | B2: Marisa Obrien | C2: carrollallison@example.com | D2: 32 | E2: Other | F2: GoPro Hero | G2: 2021-03-22 | H2: Technical issue | I2: Product setup | J2: I'm having an issue with the {product_purchased}. Please assist. Your billing zip code is: 71701. We appreciate that you have requested a website address. Please double check your email address. I've tried troubleshooting steps mentioned in the user manual, but the issue persists. | K2: Pending Customer Response | L2: Under Investigation | M2: Critical | N2: Social media | O2: 2023-06-01 12:15:36 | Q2: -1 | R2: High | S2: Pending Customer Response | T2: Billing | U2: Kevin Bacon | V2: 44971.892 | Y2: 2023-02
A3: 2 | B3: Jessica Rios | C3: clarkeashley@example.com | D3: 42 | E3: Female | F3: LG Smart TV | G3: 2021-05-22 | H3: Technical issue | I3: Peripheral compatibility | J3: I'm having an issue with the {product_purchased}. Please assist. If you need to change an existing product. I'm having an issue with the {product_purchased}. Please assist. If The issue I'm facing is intermittent. Sometimes it works fine, but other times it acts up unexpectedly. | K3: Pending Customer Response | L3: Under Investigation | M3: Critical | N3: Chat | O3: 2023-06-01 16:45:38 | Q3: -1 | R3: High | S3: Pending Customer Response | T3: Technical | U3: Bob Johnson | V3: 45602.803 | Y3: 2024-11
A4: 3 | B4: Christopher Robbins | C4: gonzalestracy@example.com | D4: 48 | E4: Other | F4: Dell XPS | G4: 2020-07-14 | H4: Technical issue | I4: Network problem | J4: I'm facing a problem with my {product_purchased}. The {product_purchased} is not turning on. It was working fine until yesterday, but now it doesn't respond. 1.8.3 I really I'm using the original charger that came with my {product_purchased}, but it's not charging properly. | K4: Closed | L4: Case maybe show recently my computer follow. | M4: Low | N4: Social media | O4: 2023-06-01 11:14:38 | P4: 2023-06-01 18:05:38 | Q4: 3 | R4: Low | S4: Closed | T4: Billing | U4: Alice Smith | V4: 45363.304 | W4: 2024-03-12 22:19:50.846893311 | X4: 15.03 | Y4: 2024-03
A5: 4 | B5: Christina Dillon | C5: bradleyolson@example.org | D5: 27 | E5: Female | F5: Microsoft Office | G5: 2020-11-13 | H5: Billing inquiry | I5: Account access | J5: I'm having an issue with the {product_purchased}. Please assist. If you have a problem you're interested in and I'd love to see this happen, please check out the Feedback. I've already contacted customer support multiple times, but the issue remains unresolved. | K5: Closed | L5: Try capital clearly never color toward story. | M5: Low | N5: Social media | O5: 2023-06-01 07:29:40 | P5: 2023-06-01 01:57:40 | Q5: 3 | R5: Low | S5: Closed | T5: Login | U5: Laura Croft | V5: 45217.302 | W5: 2023-10-20 22:59:05.872913361 | X5: 63.74 | Y5: 2023-10
A6: 5 | B6: Alexander Carroll | C6: bradleymark@example.com | D6: 67 | E6: Female | F6: Autodesk AutoCAD | G6: 2020-02-04 | H6: Billing inquiry | I6: Data loss | J6: I'm having an issue with the {product_purchased}. Please assist. Note: The seller is not responsible for any damages arising out of the delivery of the battleground game. Please have the game in good condition and shipped to you I've noticed a sudden decrease in battery life on my {product_purchased}. It used to last much longer. | K6: Closed | L6: West decision evidence bit. | M6: Low | N6: Email | O6: 2023-06-01 00:12:42 | P6: 2023-06-01 19:53:42 | Q6: 1 | R6: Low | S6: Closed | T6: Shipping | U6: Ethan Hunt | V6: 44732.611 | W6: 2022-06-21 00:32:23.534978151 | X6: 9.87 | Y6: 2022-06
A7: 6 | B7: Rebecca Fleming | C7: sheenasmith@example.com | D7: 53 | E7: Male | F7: Microsoft Office | G7: 2020-07-28 | H7: Cancellation request | I7: Payment issue | J7: I'm facing a problem with my {product_purchased}. The {product_purchased} is not turning on. It was working fine until yesterday, but now it doesn't respond. To remove the new {product_purch I've checked for any available software updates for my {product_purchased}, but there are none. | K7: Open | L7: Under Investigation | M7: Low | N7: Social media | Q7: -1 | R7: Low | S7: Open | T7: Billing | U7: Diana Prince | V7: 44732.585 | Y7: 2022-06
A8: 7 | B8: Jacqueline Wright | C8: donaldkeith@example.org | D8: 24 | E8: Other | F8: Microsoft Surface | G8: 2020-02-23 | H8: Product inquiry | I8: Refund request | J8: I'm unable to access my {product_purchased} account. It keeps displaying an 'Invalid Credentials' error, even though I'm using the correct login information. How can I regain access to my account? Solution 1 I'm unable to find the option to perform the desired action in the {product_purchased}. Could you please guide me through the steps? | K8: Open | L8: Under Investigation | M8: Critical | N8: Social media | Q8: -1 | R8: High | S8: Open | T8: Refund | U8: Diana Prince | V8: 44625.372 | Y8: 2022-03
A9: 8 | B9: Denise Lee | C9: joelwilliams@example.com | D9: 23 | E9: Male | F9: Philips Hue Lights | G9: 2020-08-09 | H9: Refund request | I9: Battery life | J9: I'm having an issue with the {product_purchased}. Please assist. (Thanks) I will contact all my suppliers and confirm. Please try and find out whether their inventory is currently stocked, or any other reason. I am I've performed a factory reset on my {product_purchased}, hoping it would resolve the problem, but it didn't help. | K9: Open | L9: Under Investigation | M9: Critical | N9: Social media | Q9: -1 | R9: High | S9: Open | T9: Login | U9: Charlie Brown | V9: 45510.234 | Y9: 2024-08
A10: 9 | B10: Nicolas Wilson | C10: joshua24@example.com | D10: 60 | E10: Other | F10: Fitbit Versa Smartwatch | G10: 2020-07-16 | H10: Technical issue | I10: Installation support | J10: I'm having an issue with the {product_purchased}. Please assist. Thank you. {product_purchased} is not the exact type you might prefer, they use the exact same method for different uses. Please help I've recently updated the firmware of my {product_purchased}, and the issue started happening afterward. Could it be related to the update? | K10: Pending Customer Response | L10: Under Investigation | M10: Low | N10: Social media | O10: 2023-06-01 10:32:47 | Q10: -1 | R10: Low | S10: Pending Customer Response | T10: Technical | U10: Laura Croft | V10: 45219.992 | Y10: 2023-10
A11: 10 | B11: William Dawson | C11: clopez@example.com | D11: 27 | E11: Male | F11: Dyson Vacuum Cleaner | G11: 2020-03-06 | H11: Refund request | I11: Payment issue | J11: My {product_purchased} is making strange noises and not functioning properly. I suspect there might be a hardware issue. Can you please help me with this? } If we can, please send a "request" to dav The issue I'm facing is intermittent. Sometimes it works fine, but other times it acts up unexpectedly. | K11: Pending Customer Response | L11: Under Investigation | M11: Critical | N11: Phone | O11: 2023-06-01 09:25:48 | Q11: -1 | R11: High | S11: Pending Customer Response | T11: Billing | U11: Bob Johnson | V11: 45337.11 | Y11: 2024-02
A12: 11 | B12: Joseph Moreno | C12: mbrown@example.org | D12: 48 | E12: Male | F12: Nintendo Switch | G12: 2021-01-19 | H12: Cancellation request | I12: Data loss | J12: I'm having an issue with the {product_purchased}. Please assist. 1-800-799-0808. Product Search: What's New in 2-3-4-5? Report Feedback Customer Service is your best I'm using the original charger that came with my {product_purchased}, but it's not charging properly. | K12: Closed | L12: Measure tonight surface feel forward. | M12: High | N12: Phone | O12: 2023-06-01 17:46:49 | P12: 2023-05-31 23:51:49 | Q12: 1 | R12: High | S12: Closed | T12: Billing | U12: Kevin Bacon | V12: 44584.311 | W12: 2022-01-27 12:00:37.836337328 | X12: 100.55 | Y12: 2022-01
A13: 12 | B13: Brandon Arnold | C13: davisjohn@example.net | D13: 51 | E13: Male | F13: Microsoft Xbox Controller | G13: 2021-10-24 | H13: Product inquiry | I13: Software bug | J13: I'm having an issue with the {product_purchased}. Please assist. 4. It is possible that we cannot find some type of text or a product name to identify someone like Mr. Brown. 5. On the I've reviewed the troubleshooting steps on the official support website, but they didn't resolve the problem. | K13: Closed | L13: Measure there house management pick knowledge trade. | M13: High | N13: Chat | O13: 2023-06-01 12:05:51 | P13: 2023-06-01 09:27:51 | Q13: 1 | R13: High | S13: Closed | T13: Technical | U13: Laura Croft | V13: 45623.822 | W13: 2024-11-28 13:02:27.293341875 | X13: 17.31 | Y13: 2024-11
A14: 13 | B14: Tamara Hahn | C14: jensenwilliam@example.net | D14: 27 | E14: Other | F14: Nintendo Switch Pro Controller | G14: 2021-05-26 | H14: Technical issue | I14: Hardware issue | J14: I'm having an issue with the {product_purchased}. Please assist. CQW: Why didn't I send him the invoice? Thanks a lot. L: He's like the best customer I've met. I've noticed that the issue occurs consistently when I use a specific feature or application on my {product_purchased}. | K14: Pending Customer Response | L14: Under Investigation | M14: Low | N14: Chat | O14: 2023-06-01 19:03:53 | Q14: -1 | R14: Low | S14: Pending Customer Response | T14: Billing | U14: Oliver Twist | V14: 45473.296 | Y14: 2024-06
A15: 14 | B15: Sandra Barnes | C15: gwendolyn51@example.net | D15: 65 | E15: Other | F15: Nest Thermostat | G15: 2020-07-13 | H15: Technical issue | I15: Product setup | J15: I've recently set up my {product_purchased}, but it fails to connect to any available networks. What steps should I take to troubleshoot this issue? I can't find the 'Product_IP' field of the I'm concerned about the security of my {product_purchased} and would like to ensure that my data is safe. | K15: Pending Customer Response | L15: Under Investigation | M15: Low | N15: Chat | O15: 2023-06-01 20:34:54 | Q15: -1 | R15: Low | S15: Pending Customer Response | T15: Technical | U15: Ian Malcolm | V15: 44794.282 | Y15: 2022-08
A16: 15 | B16: Amy Hill | C16: medinasteven@example.net | D16: 48 | E16: Female | F16: Sony PlayStation | G16: 2020-02-29 | H16: Billing inquiry | I16: Product setup | J16: I'm having an issue with the {product_purchased}. Please assist. Product Name: TPUBASK3E3KQ0 Join Date: Oct 2007 Posts: 11,532 Quote: I've recently updated the firmware of my {product_purchased}, and the issue started happening afterward. Could it be related to the update? | K16: Closed | L16: Officer moment world sing parent available. | M16: High | N16: Chat | O16: 2023-06-01 06:22:55 | P16: 2023-05-31 23:08:55 | Q16: 4 | R16: High | S16: Closed | T16: Shipping | U16: Bob Johnson | V16: 44760.869 | W16: 2022-07-23 05:55:48.497529268 | X16: 105.07 | Y16: 2022-07
A17: 16 | B17: Elizabeth Foley | C17: amy41@example.net | D17: 18 | E17: Other | F17: GoPro Action Camera | G17: 2021-06-24 | H17: Billing inquiry | I17: Product recommendation | J17: I'm having an issue with the {product_purchased}. Please assist. Please note, you might have already paid for this product, which means spectators are not buying any of the products from the sale as their donations will go straight I've noticed a sudden decrease in battery life on my {product_purchased}. It used to last much longer. | K17: Pending Customer Response | L17: Under Investigation | M17: High | N17: Social media | O17: 2023-06-01 15:09:57 | Q17: -1 | R17: High | S17: Pending Customer Response | T17: Technical | U17: Julia Roberts | V17: 44762.599 | Y17: 2022-07
A18: 17 | B18: Julia Salazar | C18: watkinsbarbara@example.com | D18: 63 | E18: Other | F18: Xbox | G18: 2021-10-13 | H18: Product inquiry | I18: Account access | J18: I'm having an issue with the {product_purchased}. Please assist. - Acknowledgement: Thanks to Dan for the tip. When you purchase a new product from my store or from your local retailer, they will also provide I'm concerned about the security of my {product_purchased} and would like to ensure that my data is safe. | K18: Closed | L18: Seek evidence book collection catch. | M18: Critical | N18: Chat | O18: 2023-06-01 19:46:59 | P18: 2023-06-01 15:58:59 | Q18: 4 | R18: High | S18: Closed | T18: Login | U18: George Clark | V18: 44894.916 | W18: 2022-11-30 23:50:10.121916056 | X18: 25.85 | Y18: 2022-11
A19: 18 | B19: Joshua Castillo | C19: mooredeborah@example.org | D19: 56 | E19: Female | F19: Microsoft Xbox Controller | G19: 2020-09-07 | H19: Product inquiry | I19: Payment issue | J19: I'm having an issue with the {product_purchased}. Please assist. Thanks!" * [0] - [0] - [0] - [0] If this product is sold and you have not used any I've reviewed the troubleshooting steps on the official support website, but they didn't resolve the problem. | K19: Pending Customer Response | L19: Under Investigation | M19: High | N19: Chat | O19: 2023-06-01 21:05:01 | Q19: -1 | R19: High | S19: Pending Customer Response | T19: Billing | U19: Alice Smith | V19: 45136.379 | Y19: 2023-07
A20: 19 | B20: Wendy Davis | C20: brenda20@example.net | D20: 19 | E20: Male | F20: LG Washing Machine | G20: 2021-09-23 | H20: Product inquiry | I20: Peripheral compatibility | J20: I'm having an issue with the {product_purchased}. Please assist. I want to be an active member of our community on YouTube... The issue I'm facing is intermittent. Sometimes it works fine, but other times it acts up unexpectedly. | K20: Open | L20: Under Investigation | M20: High | N20: Social media | Q20: -1 | R20: High | S20: Open | T20: Account | U20: Alice Smith | V20: 45034.751 | Y20: 2023-04
A21: 20 | B21: Jeffrey Robertson | C21: jameslopez@example.com | D21: 39 | E21: Female | F21: Canon EOS | G21: 2021-03-08 | H21: Refund request | I21: Software bug | J21: I'm having an issue with the {product_purchased}. Please assist. I'm having an issue with the product_purchased}. Please assist. Customer Reviewer: My Husband was able to take an order from Apple I've checked for any available software updates for my {product_purchased}, but there are none. | K21: Closed | L21: Wish mouth build resource though. | M21: Low | N21: Chat | O21: 2023-06-01 00:46:04 | P21: 2023-06-01 20:29:04 | Q21: 5 | R21: Low | S21: Closed | T21: Technical | U21: Bob Johnson | V21: 44880.667 | W21: 2022-11-18 03:16:18.495856285 | X21: 59.27 | Y21: 2022-11
A22: 21 | B22: Suzanne Holmes | C22: rogermcgrath@example.net | D22: 28 | E22: Other | F22: HP Pavilion | G22: 2021-05-31 | H22: Refund request | I22: Payment issue | J22: I'm having an issue with the {product_purchased}. Please assist. " -name "Microsoft Surface Pro. " " -version 1.10.2 "1.10.2" " -usage I've checked for any available software updates for my {product_purchased}, but there are none. | K22: Pending Customer Response | L22: Under Investigation | M22: High | N22: Chat | O22: 2023-06-01 05:08:05 | Q22: -1 | R22: High | S22: Pending Customer Response | T22: Billing | U22: Diana Prince | V22: 45231.75 | Y22: 2023-11
A23: 22 | B23: Tanner Conley | C23: zbond@example.net | D23: 66 | E23: Male | F23: Fitbit Versa Smartwatch | G23: 2020-02-04 | H23: Cancellation request | I23: Installation support | J23: I'm having an issue with the {product_purchased}. Please assist. The email address should change to: customer@julietr.com, as there is a unique id number unique for each product. You I've tried different settings and configurations on my {product_purchased}, but the issue persists. | K23: Pending Customer Response | L23: Under Investigation | M23: Critical | N23: Social media | O23: 2023-05-31 23:57:07 | Q23: -1 | R23: High | S23: Pending Customer Response | T23: Shipping | U23: Diana Prince | V23: 44714.517 | Y23: 2022-06
A24: 23 | B24: Stephanie Nelson DVM | C24: ljohnson@example.org | D24: 54 | E24: Female | F24: Xbox | G24: 2020-02-11 | H24: Cancellation request | I24: Delivery problem | J24: I'm having an issue with the {product_purchased}. Please assist. (And if need be this time, that could help.) 1.3.2.1 Update my version to 3.0 or more. The issue I'm facing is intermittent. Sometimes it works fine, but other times it acts up unexpectedly. | K24: Open | L24: Under Investigation | M24: Medium | N24: Social media | Q24: -1 | R24: Medium | S24: Open | T24: Shipping | U24: Ian Malcolm | V24: 44881.669 | Y24: 2022-11
A25: 24 | B25: Antonio Scott | C25: carlsonmatthew@example.org | D25: 63 | E25: Female | F25: Nintendo Switch Pro Controller | G25: 2021-08-06 | H25: Technical issue | I25: Refund request | J25: I'm having an issue with the {product_purchased}. Please assist. I'll take care of those. I've performed a factory reset on my {product_purchased}, hoping it would resolve the problem, but it didn't help. | K25: Pending Customer Response | L25: Under Investigation | M25: Low | N25: Social media | O25: 2023-06-01 09:06:09 | Q25: -1 | R25: Low | S25: Pending Customer Response | T25: Refund | U25: Julia Roberts | V25: 44962.937 | Y25: 2023-02
A26: 25 | B26: John Cuevas | C26: lbarron@example.org | D26: 19 | E26: Male | F26: Amazon Kindle | G26: 2021-05-25 | H26: Product inquiry | I26: Display issue | J26: I'm having an issue with the {product_purchased}. Please assist. {product_purchased} does not represent the price which you received by the day immediately before the shipment date. In many cases, this is the I've noticed a sudden decrease in battery life on my {product_purchased}. It used to last much longer. | K26: Open | L26: Under Investigation | M26: Critical | N26: Email | Q26: -1 | R26: High | S26: Open | T26: Billing | U26: Alice Smith | V26: 45061.167 | Y26: 2023-05
A27: 26 | B27: Gregory Bautista | C27: johnstonbeth@example.com | D27: 35 | E27: Other | F27: HP Pavilion | G27: 2021-07-05 | H27: Product inquiry | I27: Refund request | J27: My {product_purchased} is making strange noises and not functioning properly. I suspect there might be a hardware issue. Can you please help me with this? Thank you, Thank you for posting. It took me a I'm experiencing this issue on multiple devices of the same model, so it seems to be a widespread problem. | K27: Pending Customer Response | L27: Under Investigation | M27: Medium | N27: Social media | O27: 2023-06-01 19:02:12 | Q27: -1 | R27: Medium | S27: Pending Customer Response | T27: Refund | U27: Ian Malcolm | V27: 45421.539 | Y27: 2024-05
A28: 27 | B28: Ryan Sharp | C28: pmercado@example.org | D28: 22 | E28: Other | F28: Lenovo ThinkPad | G28: 2020-05-02 | H28: Billing inquiry | I28: Cancellation request | J28: I'm encountering a software bug in the {product_purchased}. Whenever I try to perform a specific action, the application crashes. Are there any updates or fixes available? On Windows Vista, this is not possible. If you are I've performed a factory reset on my {product_purchased}, hoping it would resolve the problem, but it didn't help. | K28: Pending Customer Response | L28: Under Investigation | M28: Low | N28: Social media | O28: 2023-06-01 20:02:13 | Q28: -1 | R28: Low | S28: Pending Customer Response | T28: Login | U28: Diana Prince | V28: 44780.414 | Y28: 2022-08
A29: 28 | B29: Michael Mcdowell | C29: jeffersonmichael@example.net | D29: 21 | E29: Other | F29: Fitbit Charge | G29: 2020-10-12 | H29: Cancellation request | I29: Product setup | J29: I'm having an issue with the {product_purchased}. Please assist. {{product_purchased}} must be a valid email address for your order and are valid for one week in advance. Please make your purchases as quickly as possible The issue I'm facing is intermittent. Sometimes it works fine, but other times it acts up unexpectedly. | K29: Open | L29: Under Investigation | M29: High | N29: Phone | Q29: -1 | R29: High | S29: Open | T29: Shipping | U29: Laura Croft | V29: 45124.858 | Y29: 2023-07
A30: 29 | B30: Christine Wang | C30: garciastacy@example.com | D30: 30 | E30: Other | F30: Fitbit Charge | G30: 2020-06-10 | H30: Technical issue | I30: Product recommendation | J30: I'm having an issue with the {product_purchased}. Please assist. Thank you." A statement from the consumer group had been released by Microsoft late on Tuesday afternoon. "The purchase of this product was made using a contract with I'm using the original charger that came with my {product_purchased}, but it's not charging properly. | K30: Closed | L30: Soldier we such inside. | M30: Critical | N30: Phone | O30: 2023-05-31 23:17:17 | P30: 2023-06-01 06:03:17 | Q30: 5 | R30: High | S30: Closed | T30: Billing | U30: Kevin Bacon | V30: 45210.465 | W30: 2023-10-12 00:48:17.530900002 | X30: 13.65 | Y30: 2023-10
A31: 30 | B31: Austin George | C31: shericase@example.net | D31: 67 | E31: Male | F31: Xbox | G31: 2020-12-26 | H31: Cancellation request | I31: Cancellation request | J31: I'm having an issue with the {product_purchased}. Please assist. It's not possible to remove the missing content. I've already contacted customer support multiple times, but the issue remains unresolved. | K31: Closed | L31: Firm sort voice above which site arrive. | M31: Medium | N31: Phone | O31: 2023-06-01 00:54:17 | P31: 2023-06-01 18:23:17 | Q31: 1 | R31: Medium | S31: Closed | T31: Technical | U31: Laura Croft | V31: 44612.634 | W31: 2022-02-23 12:35:48.646613598 | X31: 69.38 | Y31: 2022-02
A32: 31 | B32: Wendy Roberts | C32: jessicahenderson@example.net | D32: 22 | E32: Other | F32: Adobe Photoshop | G32: 2021-01-28 | H32: Billing inquiry | I32: Product setup | J32: I'm having an issue with the {product_purchased}. Please assist. I'm using a brand new product. What a strange situation. I've just purchased a brand new one. What to do? I've noticed that the issue occurs consistently when I use a specific feature or application on my {product_purchased}. | K32: Open | L32: Under Investigation | M32: Low | N32: Email | Q32: -1 | R32: Low | S32: Open | T32: Technical | U32: Ian Malcolm | V32: 45227.032 | Y32: 2023-10
A33: 32 | B33: Robert Wilson | C33: zstewart@example.org | D33: 60 | E33: Male | F33: GoPro Action Camera | G33: 2021-12-20 | H33: Technical issue | I33: Product compatibility | J33: I'm having an issue with the {product_purchased}. Please assist. The seller has sold the item for $29.89. When we receive your replacement, we will exchange the item for a full refund or exchange immediately upon I've already contacted customer support multiple times, but the issue remains unresolved. | K33: Closed | L33: Certain myself month past tree benefit. | M33: Medium | N33: Social media | O33: 2023-06-01 06:42:21 | P33: 2023-06-01 07:16:21 | Q33: 3 | R33: Medium | S33: Closed | T33: Refund | U33: George Clark | V33: 44748.495 | W33: 2022-07-10 16:33:14.293807268 | X33: 100.68 | Y33: 2022-07
A34: 33 | B34: Christina Gray | C34: greenkeith@example.net | D34: 36 | E34: Female | F34: Fitbit Charge | G34: 2021-12-07 | H34: Billing inquiry | I34: Product recommendation | J34: I've noticed a software bug in the {product_purchased} app. It's causing data loss and unexpected errors. How can I resolve this issue? I need assistance as soon as possible because it's affecting my work and productivity. | K34: Pending Customer Response | L34: Under Investigation | M34: Medium | N34: Chat | O34: 2023-06-01 19:36:21 | Q34: -1 | R34: Medium | S34: Pending Customer Response | T34: Technical | U34: Diana Prince | V34: 44633.002 | Y34: 2022-03
A35: 34 | B35: Timothy Lyons | C35: darlenelee@example.org | D35: 50 | E35: Male | F35: Autodesk AutoCAD | G35: 2021-12-09 | H35: Refund request | I35: Hardware issue | J35: I'm having an issue with the {product_purchased}. Please assist. We hope that every vendor takes the time it takes in to do the following: "Remove the product from your account - notify consumers, call them, make their I'm concerned about the security of my {product_purchased} and would like to ensure that my data is safe. | K35: Closed | L35: However financial development significant camera job every. | M35: Critical | N35: Social media | O35: 2023-06-01 02:01:23 | P35: 2023-06-01 18:25:23 | Q35: 5 | R35: High | S35: Closed | T35: Account | U35: Hannah Abbott | V35: 45600.8 | W35: 2024-11-08 02:50:30.908463478 | X35: 79.63 | Y35: 2024-11
A36: 35 | B36: Stacy Jones | C36: fernandezmark@example.org | D36: 27 | E36: Male | F36: Microsoft Xbox Controller | G36: 2021-04-09 | H36: Refund request | I36: Installation support | J36: I'm having an issue with the {product_purchased}. Please assist. 3-3 We are in, the first day, at the {product_purchased}. Please assist. 3-2 Please assist us I've recently updated the firmware of my {product_purchased}, and the issue started happening afterward. Could it be related to the update? | K36: Pending Customer Response | L36: Under Investigation | M36: Low | N36: Chat | O36: 2023-06-01 20:50:24 | Q36: -1 | R36: Low | S36: Pending Customer Response | T36: Technical | U36: Julia Roberts | V36: 45619.138 | Y36: 2024-11
A37: 36 | B37: Joann King | C37: jessica10@example.org | D37: 24 | E37: Other | F37: GoPro Hero | G37: 2020-10-13 | H37: Cancellation request | I37: Product recommendation | J37: I've recently set up my {product_purchased}, but it fails to connect to any available networks. What steps should I take to troubleshoot this issue? If you know the answer, please let me know. Do I I've noticed a sudden decrease in battery life on my {product_purchased}. It used to last much longer. | K37: Closed | L37: Reach paper ability effort learn. | M37: High | N37: Chat | O37: 2023-06-01 07:56:25 | P37: 2023-06-01 00:14:25 | Q37: 1 | R37: High | S37: Closed | T37: Technical | U37: Ethan Hunt | V37: 45446.966 | W37: 2024-06-06 15:13:56.310602188 | X37: 64.05 | Y37: 2024-06
A38: 37 | B38: Ruben Henry | C38: katherinehoward@example.net | D38: 65 | E38: Female | F38: Canon EOS | G38: 2020-03-14 | H38: Refund request | I38: Hardware issue | J38: I'm having an issue with the {product_purchased}. Please assist. I have to ask for support from you, the customers, before the item's arrival and I can't do that. In the short term, will you pay me I've followed the troubleshooting steps mentioned in the user manual, but the issue persists. | K38: Pending Customer Response | L38: Under Investigation | M38: Medium | N38: Email | O38: 2023-06-01 15:51:28 | Q38: -1 | R38: Medium | S38: Pending Customer Response | T38: Technical | U38: Michael Scott | V38: 44895.323 | Y38: 2022-11
A39: 38 | B39: Morgan Wagner | C39: elizabethlamb@example.com | D39: 39 | E39: Female | F39: Amazon Kindle | G39: 2020-09-02 | H39: Product inquiry | I39: Product compatibility | J39: I've forgotten my password for my {product_purchased} account, and the password reset option is not working. How can I recover my account? I can reset my password by entering the following: My password still valid: password is expired I've recently updated the firmware of my {product_purchased}, and the issue started happening afterward. Could it be related to the update? | K39: Open | L39: Under Investigation | M39: Medium | N39: Chat | Q39: -1 | R39: Medium | S39: Open | T39: Login | U39: Nancy Drew | V39: 44668.722 | Y39: 2022-04
A40: 39 | B40: Kevin Ingram | C40: victor62@example.net | D40: 19 | E40: Male | F40: Google Pixel | G40: 2021-09-10 | H40: Technical issue | I40: Account access | J40: I'm having an issue with the {product_purchased}. Please assist. 1. Do I need to purchase a refund? There is a way to purchase a refund from ZEROHITS, but there's not a I'm unable to find the option to perform the desired action in the {product_purchased}. Could you please guide me through the steps? | K40: Closed | L40: North second between this cell opportunity movement. | M40: Critical | N40: Phone | O40: 2023-06-01 18:45:30 | P40: 2023-05-31 21:53:30 | Q40: 3 | R40: High | S40: Closed | T40: Refund | U40: Alice Smith | V40: 45311.006 | W40: 2024-01-23 12:54:14.172262192 | X40: 84.76 | Y40: 2024-01
A41: 40 | B41: Michael Oneal | C41: stevenburns@example.net | D41: 33 | E41: Other | F41: Amazon Echo | G41: 2021-10-22 | H41: Product inquiry | I41: Account access | J41: I'm having an issue with the {product_purchased}. Please assist. I have a new account in the system and a new user. I'm having this issue Error: [System.CollectedMessage.ThrowBack I'm concerned about the security of my {product_purchased} and would like to ensure that my data is safe. | K41: Pending Customer Response | L41: Under Investigation | M41: Medium | N41: Social media | O41: 2023-05-31 22:19:32 | Q41: -1 | R41: Medium | S41: Pending Customer Response | T41: Login | U41: Michael Scott | V41: 45043.738 | Y41: 2023-04
A42: 41 | B42: Casey Tran | C42: shawn54@example.net | D42: 19 | E42: Female | F42: PlayStation | G42: 2021-02-07 | H42: Product inquiry | I42: Installation support | J42: I've recently set up my {product_purchased}, but it fails to connect to any available networks. What steps should I take to troubleshoot this issue? The next step is to resolve this issue if the user is not I've noticed that the issue occurs consistently when I use a specific feature or application on my {product_purchased}. | K42: Pending Customer Response | L42: Under Investigation | M42: Low | N42: Phone | O42: 2023-06-01 09:11:33 | Q42: -1 | R42: Low | S42: Pending Customer Response | T42: Technical | U42: Michael Scott | V42: 44695.403 | Y42: 2022-05
A43: 42 | B43: Katie Mitchell | C43: sheila78@example.org | D43: 35 | E43: Male | F43: Dell XPS | G43: 2021-06-09 | H43: Billing inquiry | I43: Product compatibility | J43: I'm facing a problem with my {product_purchased}. The {product_purchased} is not turning on. It was working fine until yesterday, but now it doesn't respond. If I'd just switched to a The issue I'm facing is intermittent. Sometimes it works fine, but other times it acts up unexpectedly. | K43: Closed | L43: Start book field officer seem make. | M43: Critical | N43: Chat | O43: 2023-06-01 20:25:34 | P43: 2023-06-01 14:43:34 | Q43: 3 | R43: High | S43: Closed | T43: Technical | U43: Charlie Brown | V43: 45103.99 | W43: 2023-06-28 07:56:57.111807108 | X43: 32.2 | Y43: 2023-06
A44: 43 | B44: Justin Giles | C44: woodmargaret@example.org | D44: 22 | E44: Male | F44: Samsung Galaxy | G44: 2020-10-10 | H44: Product inquiry | I44: Product compatibility | J44: I'm having an issue with the {product_purchased}. Please assist. The product_purchased attribute does not exist on your user's product. This is so that you can configure the {product_purchased} I need assistance as soon as possible because it's affecting my work and productivity. | K44: Pending Customer Response | L44: Under Investigation | M44: Medium | N44: Phone | O44: 2023-06-01 18:41:35 | Q44: -1 | R44: Medium | S44: Pending Customer Response | T44: Technical | U44: Laura Croft | V44: 44599.426 | Y44: 2022-02
A45: 44 | B45: Michael Allison | C45: abowen@example.org | D45: 54 | E45: Female | F45: iPhone | G45: 2020-01-16 | H45: Technical issue | I45: Hardware issue | J45: I'm having an issue with the {product_purchased}. Please assist. Thank you." The issue occurred after Amazon started a tool to deal with a problem like this (see page 36 of the FAQ): "The product is not I've recently updated the firmware of my {product_purchased}, and the issue started happening afterward. Could it be related to the update? | K45: Open | L45: Under Investigation | M45: Low | N45: Email | Q45: -1 | R45: Low | S45: Open | T45: Technical | U45: George Clark | V45: 45557.477 | Y45: 2024-09
A46: 45 | B46: Donald Gibbs | C46: laura33@example.org | D46: 34 | E46: Other | F46: HP Pavilion | G46: 2021-09-25 | H46: Refund request | I46: Product compatibility | J46: I'm having an issue with the {product_purchased}. Please assist. I wanted a picture for my 3DS, but I already bought a lot of items, so I found an online cart: "Fountain of Dreams Collection I'm unable to find the option to perform the desired action in the {product_purchased}. Could you please guide me through the steps? | K46: Closed | L46: Over read region lawyer much speech control. | M46: Critical | N46: Email | O46: 2023-06-01 05:58:39 | P46: 2023-06-01 03:19:39 | Q46: 2 | R46: High | S46: Closed | T46: Technical | U46: Fiona Gallagher | V46: 44845.135 | W46: 2022-10-13 00:28:04.499214411 | X46: 45.23 | Y46: 2022-10
A47: 46 | B47: Timothy Sutton | C47: david40@example.org | D47: 65 | E47: Female | F47: LG Smart TV | G47: 2021-02-01 | H47: Product inquiry | I47: Cancellation request | J47: I'm having an issue with the {product_purchased}. Please assist. Thanks". "As a result I'm having an issue with the 1.0 patch. Please assist." "All I'm asking is to update I'm concerned about the security of my {product_purchased} and would like to ensure that my data is safe. | K47: Open | L47: Under Investigation | M47: Low | N47: Chat | Q47: -1 | R47: Low | S47: Open | T47: Technical | U47: Ethan Hunt | V47: 45287.233 | Y47: 2023-12
A48: 47 | B48: Cassandra Richards | C48: abigail06@example.com | D48: 50 | E48: Female | F48: Nintendo Switch Pro Controller | G48: 2020-10-15 | H48: Refund request | I48: Network problem | J48: I'm having an issue with the {product_purchased}. Please assist. We have not yet provided an address or a name for this product. If this website does not exist, please contact us with this information and we will provide it. I need assistance as soon as possible because it's affecting my work and productivity. | K48: Closed | L48: Audience food pretty cut. | M48: High | N48: Phone | O48: 2023-06-01 03:43:43 | P48: 2023-06-01 09:24:43 | Q48: 1 | R48: High | S48: Closed | T48: Technical | U48: Charlie Brown | V48: 44903.094 | W48: 2022-12-11 03:46:01.486666918 | X48: 73.5 | Y48: 2022-12
A49: 48 | B49: Kristen Perry | C49: bevans@example.org | D49: 27 | E49: Female | F49: GoPro Hero | G49: 2020-07-29 | H49: Technical issue | I49: Software bug | J49: I'm having an issue with the {product_purchased}. Please assist. This product is not found on, and should NOT come from, this site. Not sure about what this product covers? Product Description I'm experiencing this issue on multiple devices of the same model, so it seems to be a widespread problem. | K49: Closed | L49: Late center interview that. | M49: Medium | N49: Social media | O49: 2023-06-01 07:16:45 | P49: 2023-06-01 05:59:45 | Q49: 1 | R49: Medium | S49: Closed | T49: Technical | U49: Diana Prince | V49: 45131.245 | W49: 2023-07-24 16:14:51.347590446 | X49: 10.36 | Y49: 2023-07
A50: 49 | B50: Noah Mcknight | C50: juliepowers@example.org | D50: 32 | E50: Other | F50: LG OLED | G50: 2021-02-15 | H50: Cancellation request | I50: Network problem | J50: I'm having an issue with the {product_purchased}. Please assist. Please. Don't. Don't see my issue? Please contact me. I'm unable to find the option to perform the desired action in the {product_purchased}. Could you please guide me through the steps? | K50: Open | L50: Under Investigation | M50: High | N50: Chat | Q50: -1 | R50: High | S50: Open | T50: Technical | U50: Michael Scott | V50: 45160.419 | Y50: 2023-08
A51: 50 | B51: Katie Johnson | C51: thomas46@example.net | D51: 44 | E51: Male | F51: Microsoft Office | G51: 2020-09-27 | H51: Technical issue | I51: Display issue | J51: I'm having an issue with the {product_purchased}. Please assist. If you've received a refund, please contact Customer Service. Otherwise, please call us at 303.938.2837. I'm having an issue with the I'm concerned about the security of my {product_purchased} and would like to ensure that my data is safe. | K51: Open | L51: Under Investigation | M51: Medium | N51: Chat | Q51: -1 | R51: Medium | S51: Open | T51: Refund | U51: Fiona Gallagher | V51: 44764.186 | Y51: 2022-07
A52: 51 | B52: Kayla Dunn | C52: ramirezphilip@example.net | D52: 66 | E52: Male | F52: Sony Xperia | G52: 2020-12-22 | H52: Refund request | I52: Software bug | J52: I'm encountering a software bug in the {product_purchased}. Whenever I try to perform a specific action, the application crashes. Are there any updates or fixes available? There are several packages that run in memory by default. These I'm experiencing this issue on multiple devices of the same model, so it seems to be a widespread problem. | K52: Open | L52: Under Investigation | M52: Medium | N52: Chat | Q52: -1 | R52: Medium | S52: Open | T52: Technical | U52: Bob Johnson | V52: 45623.466 | Y52: 2024-11
A53: 52 | B53: Tracy White | C53: wvargas@example.com | D53: 64 | E53: Male | F53: LG Smart TV | G53: 2020-11-20 | H53: Refund request | I53: Software bug | J53: I've recently set up my {product_purchased}, but it fails to connect to any available networks. What steps should I take to troubleshoot this issue?.......................................................1. Visit https://forum.ejconop I've reviewed the troubleshooting steps on the official support website, but they didn't resolve the problem. | K53: Closed | L53: Might Mrs often stuff. | M53: Medium | N53: Chat | O53: 2023-06-01 16:21:49 | P53: 2023-06-01 10:31:49 | Q53: 3 | R53: Medium | S53: Closed | T53: Technical | U53: Bob Johnson | V53: 45410.541 | W53: 2024-05-03 04:45:02.152548313 | X53: 111.76 | Y53: 2024-04
A54: 53 | B54: Christian Graves | C54: hgriffin@example.org | D54: 54 | E54: Male | F54: Nest Thermostat | G54: 2021-10-10 | H54: Refund request | I54: Network problem | J54: I'm having an issue with the {product_purchased}. Please assist. Please. Please. I need assistance as soon as possible because it's affecting my work and productivity. | K54: Closed | L54: More left involve agree station billion would. | M54: High | N54: Social media | O54: 2023-06-01 01:54:49 | P54: 2023-06-01 20:59:49 | Q54: 3 | R54: High | S54: Closed | T54: Technical | U54: George Clark | V54: 45590.522 | W54: 2024-10-26 15:09:43.863504887 | X54: 26.63 | Y54: 2024-10
A55: 54 | B55: Casey Reed | C55: sabrina61@example.org | D55: 37 | E55: Male | F55: HP Pavilion | G55: 2021-08-16 | H55: Cancellation request | I55: Delivery problem | J55: I'm having an issue with the {product_purchased}. Please assist. If it's not working I can't help you. I've performed a factory reset on my {product_purchased}, hoping it would resolve the problem, but it didn't help. | K55: Closed | L55: Even two pay expect. | M55: Low | N55: Chat | O55: 2023-06-01 00:39:50 | P55: 2023-06-01 10:25:50 | Q55: 4 | R55: Low | S55: Closed | T55: Shipping | U55: Bob Johnson | V55: 45541.607 | W55: 2024-09-09 02:33:09.969259024 | X55: 59.99 | Y55: 2024-09
A56: 55 | B56: Carrie Ayers | C56: natasha18@example.com | D56: 68 | E56: Female | F56: Microsoft Xbox Controller | G56: 2021-10-14 | H56: Technical issue | I56: Network problem | J56: I've noticed a software bug in the {product_purchased} app. It's causing data loss and unexpected errors. How can I resolve this issue? For those who live in the U.S., you can use the {product_ I'm unable to find the option to perform the desired action in the {product_purchased}. Could you please guide me through the steps? | K56: Pending Customer Response | L56: Under Investigation | M56: Low | N56: Chat | O56: 2023-06-01 07:25:51 | Q56: -1 | R56: Low | S56: Pending Customer Response | T56: Technical | U56: Fiona Gallagher | V56: 45216.471 | Y56: 2023-10
A57: 56 | B57: Sarah Cole | C57: williamscynthia@example.org | D57: 50 | E57: Female | F57: Nintendo Switch Pro Controller | G57: 2021-11-19 | H57: Cancellation request | I57: Software bug | J57: I'm having an issue with the {product_purchased}. Please assist. The requested address will be returned within 3 – 9 business days. Please do not hesitate to contact us using the appropriate form. (9 weeks from purchase time I'm unable to find the option to perform the desired action in the {product_purchased}. Could you please guide me through the steps? | K57: Pending Customer Response | L57: Under Investigation | M57: Critical | N57: Chat | O57: 2023-06-01 11:14:53 | Q57: -1 | R57: High | S57: Pending Customer Response | T57: Technical | U57: Nancy Drew | V57: 45571.223 | Y57: 2024-10
A58: 57 | B58: Alison Ford | C58: mcgeebrandon@example.org | D58: 69 | E58: Male | F58: Autodesk AutoCAD | G58: 2021-12-22 | H58: Technical issue | I58: Software bug | J58: I'm having an issue with the {product_purchased}. Please assist. I've noticed that the issue occurs consistently when I use a specific feature or application on my {product_purchased}. | K58: Pending Customer Response | L58: Under Investigation | M58: Medium | N58: Social media | O58: 2023-06-01 10:33:53 | Q58: -1 | R58: Medium | S58: Pending Customer Response | T58: Technical | U58: Fiona Gallagher | V58: 44658.67 | Y58: 2022-04
A59: 58 | B59: Lori Young | C59: pthomas@example.org | D59: 47 | E59: Other | F59: GoPro Action Camera | G59: 2020-07-28 | H59: Refund request | I59: Peripheral compatibility | J59: I'm having an issue with the {product_purchased}. Please assist. Thank you! This product was added to your friend's shopping cart at your friend's favorite store. Sorry, your account is not loaded. I've followed the troubleshooting steps mentioned in the user manual, but the issue persists. | K59: Open | L59: Under Investigation | M59: Critical | N59: Email | Q59: -1 | R59: High | S59: Open | T59: Account | U59: Julia Roberts | V59: 44776.372 | Y59: 2022-08
A60: 59 | B60: Kimberly Mack | C60: lwilliamson@example.net | D60: 27 | E60: Male | F60: Autodesk AutoCAD | G60: 2020-07-31 | H60: Technical issue | I60: Product recommendation | J60: I've forgotten my password for my {product_purchased} account, and the password reset option is not working. How can I recover my account? What happens when you lose all of your money without a credit card? The issue I'm facing is intermittent. Sometimes it works fine, but other times it acts up unexpectedly. | K60: Closed | L60: During base sure measure teach time large. | M60: Medium | N60: Phone | O60: 2023-06-01 11:56:57 | P60: 2023-06-01 04:45:57 | Q60: 5 | R60: Medium | S60: Closed | T60: Billing | U60: Ethan Hunt | V60: 44611.295 | W60: 2022-02-23 18:03:47.349248171 | X60: 106.99 | Y60: 2022-02
A61: 60 | B61: Samuel Schroeder | C61: andrew28@example.org | D61: 40 | E61: Other | F61: Apple AirPods | G61: 2021-09-05 | H61: Product inquiry | I61: Cancellation request | J61: I'm having an issue with the {product_purchased}. Please assist. Also note: Your information gets deleted every time an article is sent to a website you've never viewed. {Product_id} is a unique identifier in I'm not sure if this issue is specific to my device or if others have reported similar problems. | K61: Closed | L61: Reveal long fish care value direction TV. | M61: Medium | N61: Chat | O61: 2023-06-01 19:50:58 | P61: 2023-06-01 00:38:58 | Q61: 3 | R61: Medium | S61: Closed | T61: Technical | U61: Michael Scott | V61: 44918.008 | W61: 2022-12-23 11:36:39.932850838 | X61: 11.43 | Y61: 2022-12
A62: 61 | B62: Amanda Burton | C62: hannahstephens@example.com | D62: 40 | E62: Male | F62: Sony 4K HDR TV | G62: 2020-11-16 | H62: Cancellation request | I62: Product setup | J62: I'm having an issue with the {product_purchased}. Please assist. It's time for me to update the product list I'm having an issue with the{product_purchased}. Please assist. It's time for I've performed a factory reset on my {product_purchased}, hoping it would resolve the problem, but it didn't help. | K62: Closed | L62: Else personal leg break book nearly. | M62: Medium | N62: Chat | O62: 2023-06-01 00:18:00 | P62: 2023-06-01 11:55:00 | Q62: 1 | R62: Medium | S62: Closed | T62: Login | U62: Alice Smith | V62: 44987.372 | W62: 2023-03-06 09:27:33.022942543 | X62: 96.52 | Y62: 2023-03
A63: 62 | B63: Sarah Williams | C63: akelly@example.net | D63: 41 | E63: Other | F63: Lenovo ThinkPad | G63: 2021-11-21 | H63: Product inquiry | I63: Battery life | J63: I'm having an issue with the {product_purchased}. Please assist. I was able to get my $50 bag from the vendor, but the bags I was wearing in the show were covered in stickers and the price for those I've tried different settings and configurations on my {product_purchased}, but the issue persists. | K63: Pending Customer Response | L63: Under Investigation | M63: Critical | N63: Social media | O63: 2023-06-01 01:32:02 | Q63: -1 | R63: High | S63: Pending Customer Response | T63: Billing | U63: Laura Croft | V63: 44858.898 | Y63: 2022-10
A64: 63 | B64: Frank Sherman | C64: floresbryan@example.net | D64: 64 | E64: Female | F64: Xbox | G64: 2020-12-12 | H64: Billing inquiry | I64: Payment issue | J64: I'm having an issue with the {product_purchased}. Please assist. } } } function getProductCount () {orters(function ($p ) { // This gets the count for all the items in the The issue I'm facing is intermittent. Sometimes it works fine, but other times it acts up unexpectedly. | K64: Closed | L64: Eye while if exist name receive. | M64: High | N64: Email | O64: 2023-05-31 23:37:04 | P64: 2023-06-01 12:41:04 | Q64: 4 | R64: High | S64: Closed | T64: Billing | U64: Hannah Abbott | V64: 45469.238 | W64: 2024-06-26 14:52:54.265845775 | X64: 9.16 | Y64: 2024-06
A65: 64 | B65: Victoria Parker | C65: tiffany87@example.com | D65: 57 | E65: Female | F65: Adobe Photoshop | G65: 2020-04-24 | H65: Billing inquiry | I65: Hardware issue | J65: I'm having an issue with the {product_purchased}. Please assist. 4.1.7 Add a custom app icon to the app window. Click App Manager. You'll see a list of all of the new apps ( I've checked the device settings and made sure that everything is configured correctly. | K65: Pending Customer Response | L65: Under Investigation | M65: High | N65: Phone | O65: 2023-06-01 07:07:05 | Q65: -1 | R65: High | S65: Pending Customer Response | T65: Technical | U65: Ian Malcolm | V65: 44952.416 | Y65: 2023-01
A66: 65 | B66: David Smith | C66: jacob67@example.net | D66: 61 | E66: Male | F66: Microsoft Xbox Controller | G66: 2021-08-02 | H66: Technical issue | I66: Product compatibility | J66: I'm facing a problem with my {product_purchased}. The {product_purchased} is not turning on. It was working fine until yesterday, but now it doesn't respond. I'm working around this problem by switching off I've noticed a peculiar error message popping up on my {product_purchased} screen. It says '{error_message}'. What does it mean? | K66: Open | L66: Under Investigation | M66: Medium | N66: Phone | Q66: -1 | R66: Medium | S66: Open | T66: Technical | U66: Bob Johnson | V66: 44869.394 | Y66: 2022-11
A67: 66 | B67: Jeffrey Hernandez | C67: perezdana@example.org | D67: 56 | E67: Male | F67: Apple AirPods | G67: 2021-11-11 | H67: Technical issue | I67: Battery life | J67: There seems to be a glitch in the {product_purchased} software. It freezes frequently, making it difficult to use. Can you please provide a solution? "I'd love to do this on my own. It's a I've noticed a peculiar error message popping up on my {product_purchased} screen. It says '{error_message}'. What does it mean? | K67: Pending Customer Response | L67: Under Investigation | M67: Medium | N67: Phone | O67: 2023-05-31 22:38:07 | Q67: -1 | R67: Medium | S67: Pending Customer Response | T67: Technical | U67: Oliver Twist | V67: 45156.023 | Y67: 2023-08
A68: 67 | B68: John Robertson | C68: gillespiegeorge@example.com | D68: 49 | E68: Female | F68: GoPro Hero | G68: 2021-08-08 | H68: Billing inquiry | I68: Product compatibility | J68: I've noticed a software bug in the {product_purchased} app. It's causing data loss and unexpected errors. How can I resolve this issue? A good way to resolve this software issue is to use a custom configuration file The issue I'm facing is intermittent. Sometimes it works fine, but other times it acts up unexpectedly. | K68: Closed | L68: Fill young add between morning commercial. | M68: High | N68: Email | O68: 2023-06-01 05:06:08 | P68: 2023-06-01 10:17:08 | Q68: 5 | R68: High | S68: Closed | T68: Technical | U68: George Clark | V68: 44716.083 | W68: 2022-06-06 21:50:19.076412439 | X68: 67.85 | Y68: 2022-06
A69: 68 | B69: Ryan Gonzalez | C69: pwilson@example.com | D69: 54 | E69: Male | F69: Microsoft Office | G69: 2021-06-27 | H69: Cancellation request | I69: Peripheral compatibility | J69: I've accidentally deleted important data from my {product_purchased}. Is there any way to recover the deleted files? I need them urgently. What can I do to recover them? Product purchases are never recoverable from the database. I'm worried that the issue might be hardware-related and might require repair or replacement. | K69: Pending Customer Response | L69: Under Investigation | M69: Low | N69: Phone | O69: 2023-06-01 21:04:10 | Q69: -1 | R69: Low | S69: Pending Customer Response | T69: Technical | U69: Bob Johnson | V69: 45440.177 | Y69: 2024-05
A70: 69 | B70: Brianna Scott MD | C70: jbranch@example.net | D70: 51 | E70: Other | F70: Adobe Photoshop | G70: 2021-02-06 | H70: Technical issue | I70: Product compatibility | J70: I'm having an issue with the {product_purchased}. Please assist. If your product is purchased with the {product_purchased}, the {product_purchased} will be refunded. 7) Pay it I've performed a factory reset on my {product_purchased}, hoping it would resolve the problem, but it didn't help. | K70: Pending Customer Response | L70: Under Investigation | M70: Critical | N70: Chat | O70: 2023-05-31 23:00:12 | Q70: -1 | R70: High | S70: Pending Customer Response | T70: Refund | U70: Ian Malcolm | V70: 44643.404 | Y70: 2022-03
A71: 70 | B71: Michael Day | C71: william07@example.org | D71: 46 | E71: Female | F71: Canon DSLR Camera | G71: 2020-02-13 | H71: Refund request | I71: Refund request | J71: I'm unable to access my {product_purchased} account. It keeps displaying an 'Invalid Credentials' error, even though I'm using the correct login information. How can I regain access to my account? If you don't I'm concerned about the security of my {product_purchased} and would like to ensure that my data is safe. | K71: Closed | L71: Answer story series imagine discover. | M71: High | N71: Chat | O71: 2023-06-01 11:57:12 | P71: 2023-05-31 22:51:12 | Q71: 1 | R71: High | S71: Closed | T71: Refund | U71: Ethan Hunt | V71: 45642.412 | W71: 2024-12-21 02:35:55.297901630 | X71: 112.71 | Y71: 2024-12
A72: 71 | B72: Eileen Kim | C72: gabriel83@example.com | D72: 27 | E72: Male | F72: Google Pixel | G72: 2021-05-15 | H72: Cancellation request | I72: Product setup | J72: I've accidentally deleted important data from my {product_purchased}. Is there any way to recover the deleted files? I need them urgently. What about my {search } files? The {product_purchased} is the I'm using the original charger that came with my {product_purchased}, but it's not charging properly. | K72: Pending Customer Response | L72: Under Investigation | M72: Medium | N72: Chat | O72: 2023-05-31 23:49:14 | Q72: -1 | R72: Medium | S72: Pending Customer Response | T72: Billing | U72: Nancy Drew | V72: 45407.379 | Y72: 2024-04
A73: 72 | B73: Joseph Costa | C73: calvarez@example.org | D73: 37 | E73: Other | F73: iPhone | G73: 2020-09-26 | H73: Refund request | I73: Delivery problem | J73: I've recently set up my {product_purchased}, but it fails to connect to any available networks. What steps should I take to troubleshoot this issue? I've tried clearing the cache and data for the {product_purchased} app, but the issue persists. | K73: Open | L73: Under Investigation | M73: Medium | N73: Social media | Q73: -1 | R73: Medium | S73: Open | T73: Shipping | U73: Kevin Bacon | V73: 44779.365 | Y73: 2022-08
A74: 73 | B74: Tanya Powell | C74: epatel@example.org | D74: 34 | E74: Female | F74: Dyson Vacuum Cleaner | G74: 2021-02-16 | H74: Billing inquiry | I74: Display issue | J74: I'm having an issue with the {product_purchased}. Please assist. When I first noticed {product_purchased} the new price of the book was too high. I've already sent out the refund request, but they will I've checked for software updates, and my {product_purchased} is already running the latest version. | K74: Closed | L74: Executive wear gun child. | M74: Low | N74: Chat | O74: 2023-06-01 04:35:16 | P74: 2023-06-01 03:17:16 | Q74: 4 | R74: Low | S74: Closed | T74: Refund | U74: Julia Roberts | V74: 44567.818 | W74: 2022-01-08 22:42:04.456829786 | X74: 51.08 | Y74: 2022-01
A75: 74 | B75: Philip Davis | C75: fbenjamin@example.org | D75: 36 | E75: Other | F75: Fitbit Charge | G75: 2020-11-09 | H75: Cancellation request | I75: Payment issue | J75: My {product_purchased} is making strange noises and not functioning properly. I suspect there might be a hardware issue. Can you please help me with this? This is a product that must fit in a box. Please let me I've noticed a peculiar error message popping up on my {product_purchased} screen. It says '{error_message}'. What does it mean? | K75: Closed | L75: Finish common benefit most college. | M75: Critical | N75: Social media | O75: 2023-06-01 21:31:17 | P75: 2023-06-01 02:24:17 | Q75: 3 | R75: High | S75: Closed | T75: Billing | U75: Oliver Twist | V75: 45454.701 | W75: 2024-06-13 14:22:34.823255062 | X75: 45.55 | Y75: 2024-06
A76: 75 | B76: Vanessa Hayes | C76: donaldroberts@example.net | D76: 31 | E76: Female | F76: Xbox | G76: 2021-04-16 | H76: Billing inquiry | I76: Product setup | J76: I'm having an issue with the {product_purchased}. Please assist. Please, take care of such requests. [1] M.V.V. [2] The above-mentioned is made up with specific I've checked the device settings and made sure that everything is configured correctly. | K76: Open | L76: Under Investigation | M76: Critical | N76: Email | Q76: -1 | R76: High | S76: Open | T76: Technical | U76: Nancy Drew | V76: 45335.78 | Y76: 2024-02
A77: 76 | B77: Jennifer Bryan | C77: cooperthomas@example.com | D77: 37 | E77: Other | F77: Roomba Robot Vacuum | G77: 2021-01-06 | H77: Product inquiry | I77: Display issue | J77: I'm having an issue with the {product_purchased}. Please assist. 1. It is not allowed to purchase a product from an individual, or for a company in which there are no specific employees or employees, and all products have to I've followed the troubleshooting steps mentioned in the user manual, but the issue persists. | K77: Closed | L77: Somebody east painting tree sell rock level. | M77: Critical | N77: Chat | O77: 2023-06-01 14:43:20 | P77: 2023-06-01 02:30:20 | Q77: 1 | R77: High | S77: Closed | T77: Technical | U77: Fiona Gallagher | V77: 45360.034 | W77: 2024-03-12 14:24:30.154021740 | X77: 85.6 | Y77: 2024-03
A78: 77 | B78: Matthew Scott | C78: brookeross@example.net | D78: 18 | E78: Other | F78: iPhone | G78: 2020-06-30 | H78: Cancellation request | I78: Account access | J78: I'm having an issue with the {product_purchased}. Please assist. I've got a customer who has sent me a $25 invoice! I want to know if this will correct this. I just downloaded the demo and I I'm experiencing this issue on multiple devices of the same model, so it seems to be a widespread problem. | K78: Open | L78: Under Investigation | M78: Critical | N78: Phone | Q78: -1 | R78: High | S78: Open | T78: Billing | U78: Julia Roberts | V78: 45406.312 | Y78: 2024-04
A79: 78 | B79: Alfred Ortiz | C79: nicholsdouglas@example.org | D79: 63 | E79: Female | F79: Fitbit Charge | G79: 2020-12-29 | H79: Billing inquiry | I79: Delivery problem | J79: I'm having an issue with the {product_purchased}. Please assist. Product #8 4-8-0-1 The product code on your product. #Product ID : {product_id I've checked the device settings and made sure that everything is configured correctly. | K79: Closed | L79: Huge value apply born. | M79: Low | N79: Email | O79: 2023-06-01 19:16:24 | P79: 2023-06-01 15:21:24 | Q79: 5 | R79: Low | S79: Closed | T79: Shipping | U79: Diana Prince | V79: 44642.85 | W79: 2022-03-26 23:35:00.411258936 | X79: 99.19 | Y79: 2022-03
A80: 79 | B80: John Goodman | C80: vgarcia@example.com | D80: 55 | E80: Other | F80: Google Pixel | G80: 2021-01-07 | H80: Billing inquiry | I80: Data loss | J80: I'm having an issue with the {product_purchased}. Please assist. Thank you The customer's rating and reviews are important, but they don't have an impact on your credit score For over mogul financial companies who have I've performed a factory reset on my {product_purchased}, hoping it would resolve the problem, but it didn't help. | K80: Pending Customer Response | L80: Under Investigation | M80: Medium | N80: Social media | O80: 2023-06-01 16:57:26 | Q80: -1 | R80: Medium | S80: Pending Customer Response | T80: Login | U80: Laura Croft | V80: 44954.291 | Y80: 2023-01
A81: 80 | B81: Catherine Stephens | C81: hmccann@example.com | D81: 40 | E81: Other | F81: LG Smart TV | G81: 2020-11-03 | H81: Technical issue | I81: Software bug | J81: I'm having an issue with the {product_purchased}. Please assist. This is for the best experience and you can't use your phone while waiting for deliveries or when you pick it up. Please help by posting a I've tried using different cables, adapters, or peripherals with my {product_purchased}, but the issue persists. | K81: Pending Customer Response | L81: Under Investigation | M81: Critical | N81: Chat | O81: 2023-06-01 11:27:28 | Q81: -1 | R81: High | S81: Pending Customer Response | T81: Shipping | U81: Bob Johnson | V81: 44688.647 | Y81: 2022-05
A82: 81 | B82: Sarah Lee | C82: dclark@example.net | D82: 50 | E82: Other | F82: Microsoft Office | G82: 2021-03-22 | H82: Technical issue | I82: Product recommendation | J82: I'm having an issue with the {product_purchased}. Please assist. I'm unable to find the option to perform the desired action in the {product_purchased}. Could you please guide me through the steps? | K82: Pending Customer Response | L82: Under Investigation | M82: Critical | N82: Phone | O82: 2023-06-01 07:27:28 | Q82: -1 | R82: High | S82: Pending Customer Response | T82: Technical | U82: Alice Smith | V82: 45506.869 | Y82: 2024-08
A83: 82 | B83: Kiara Parker | C83: gonzalezlarry@example.org | D83: 29 | E83: Other | F83: Apple AirPods | G83: 2021-07-22 | H83: Cancellation request | I83: Cancellation request | J83: I'm encountering a software bug in the {product_purchased}. Whenever I try to perform a specific action, the application crashes. Are there any updates or fixes available? I don't know about any updates to the product. It's hard I'm unable to find the option to perform the desired action in the {product_purchased}. Could you please guide me through the steps? | K83: Pending Customer Response | L83: Under Investigation | M83: Medium | N83: Email | O83: 2023-06-01 11:37:29 | Q83: -1 | R83: Medium | S83: Pending Customer Response | T83: Technical | U83: Kevin Bacon | V83: 45244.282 | Y83: 2023-11
A84: 83 | B84: Joshua Miller | C84: kimjesse@example.com | D84: 24 | E84: Male | F84: PlayStation | G84: 2021-10-04 | H84: Refund request | I84: Software bug | J84: I'm having an issue with the {product_purchased}. Please assist. <p> A full time customer service representative will arrive soon. <p> If you would like to respond to a message I've tried different settings and configurations on my {product_purchased}, but the issue persists. | K84: Closed | L84: Event see dinner home. | M84: Low | N84: Social media | O84: 2023-06-01 05:40:30 | P84: 2023-06-01 20:35:30 | Q84: 1 | R84: Low | S84: Closed | T84: Technical | U84: Diana Prince | V84: 44924.104 | W84: 2022-12-30 11:52:12.335259438 | X84: 33.37 | Y84: 2022-12
A85: 84 | B85: James Jones | C85: dsilva@example.org | D85: 57 | E85: Other | F85: Autodesk AutoCAD | G85: 2021-08-11 | H85: Technical issue | I85: Installation support | J85: I'm having an issue with the {product_purchased}. Please assist. Your product may be available on other websites with the same keyword or your brand. Thank you. I've noticed a sudden decrease in battery life on my {product_purchased}. It used to last much longer. | K85: Pending Customer Response | L85: Under Investigation | M85: Critical | N85: Phone | O85: 2023-06-01 00:24:32 | Q85: -1 | R85: High | S85: Pending Customer Response | T85: Technical | U85: Michael Scott | V85: 44631.367 | Y85: 2022-03
A86: 85 | B86: David Taylor | C86: kaylapham@example.com | D86: 67 | E86: Other | F86: Microsoft Surface | G86: 2021-08-02 | H86: Technical issue | I86: Hardware issue | J86: I'm facing issues logging into my {product_purchased} account. It says my account is locked. What should I do to unlock it? Please log into your login browser and check to see if the account has been locked. I'm experiencing this issue on multiple devices of the same model, so it seems to be a widespread problem. | K86: Open | L86: Under Investigation | M86: Medium | N86: Phone | Q86: -1 | R86: Medium | S86: Open | T86: Login | U86: Ethan Hunt | V86: 44902.296 | Y86: 2022-12
A87: 86 | B87: Richard Mullen | C87: cschmidt@example.com | D87: 67 | E87: Female | F87: Canon EOS | G87: 2021-01-22 | H87: Product inquiry | I87: Peripheral compatibility | J87: I've forgotten my password for my {product_purchased} account, and the password reset option is not working. How can I recover my account? If you have not used login tokens for the previous 12 months, the login token I've reviewed the troubleshooting steps on the official support website, but they didn't resolve the problem. | K87: Open | L87: Under Investigation | M87: High | N87: Social media | Q87: -1 | R87: High | S87: Open | T87: Login | U87: Bob Johnson | V87: 44917.847 | Y87: 2022-12
A88: 87 | B88: Danielle Everett | C88: kimberlyhudson@example.com | D88: 46 | E88: Male | F88: Sony PlayStation | G88: 2020-01-18 | H88: Technical issue | I88: Product recommendation | J88: I'm having an issue with the {product_purchased}. Please assist. * * * @param {number}_item * * @return {item} @*/if (_ejection_exceeds(_proposal)) I've noticed that the issue occurs consistently when I use a specific feature or application on my {product_purchased}. | K88: Closed | L88: Represent where produce suddenly. | M88: Critical | N88: Phone | O88: 2023-06-01 18:03:35 | P88: 2023-06-01 06:23:35 | Q88: 2 | R88: High | S88: Closed | T88: Technical | U88: Nancy Drew | V88: 45360.69 | W88: 2024-03-09 23:21:01.320207596 | X88: 6.8 | Y88: 2024-03
A89: 88 | B89: Steven Thompson | C89: vaustin@example.org | D89: 55 | E89: Other | F89: Philips Hue Lights | G89: 2020-09-10 | H89: Technical issue | I89: Delivery problem | J89: I'm facing a problem with my {product_purchased}. The {product_purchased} is not turning on. It was working fine until yesterday, but now it doesn't respond. I'm using a phone now, I'm unable to find the option to perform the desired action in the {product_purchased}. Could you please guide me through the steps? | K89: Pending Customer Response | L89: Under Investigation | M89: High | N89: Social media | O89: 2023-06-01 19:21:36 | Q89: -1 | R89: High | S89: Pending Customer Response | T89: Shipping | U89: Diana Prince | V89: 45259.896 | Y89: 2023-11
A90: 89 | B90: Renee White | C90: chelsea84@example.org | D90: 42 | E90: Other | F90: Nikon D | G90: 2021-08-01 | H90: Billing inquiry | I90: Product setup | J90: I'm having an issue with the {product_purchased}. Please assist. Product Purchasing Error Product Purchasing Error Yes | No 28 - 30 28 - 30 32 | Product Purchasing Error | Product Purchase Error I've reviewed the troubleshooting steps on the official support website, but they didn't resolve the problem. | K90: Open | L90: Under Investigation | M90: Critical | N90: Email | Q90: -1 | R90: High | S90: Open | T90: Technical | U90: Nancy Drew | V90: 45533.269 | Y90: 2024-08
A91: 90 | B91: Lisa Hill | C91: hinescarrie@example.org | D91: 40 | E91: Male | F91: Sony Xperia | G91: 2020-01-30 | H91: Product inquiry | I91: Product recommendation | J91: I'm having an issue with the {product_purchased}. Please assist. If your computer is connected to a power source, please do not open the {product_purchased}. Please assist. If your router is wired up I've already contacted customer support multiple times, but the issue remains unresolved. | K91: Closed | L91: Exactly red two dog. | M91: Medium | N91: Email | O91: 2023-05-31 23:17:40 | P91: 2023-06-01 03:09:40 | Q91: 5 | R91: Medium | S91: Closed | T91: Technical | U91: Bob Johnson | V91: 45078.846 | W91: 2023-06-02 06:37:05.639721632 | X91: 10.31 | Y91: 2023-06
A92: 91 | B92: Sandra Bass | C92: jamesbaxter@example.com | D92: 57 | E92: Other | F92: Sony Xperia | G92: 2020-10-15 | H92: Refund request | I92: Software bug | J92: I've forgotten my password for my {product_purchased} account, and the password reset option is not working. How can I recover my account? - The password reset option can be enabled by using the {Product_purchased} The issue I'm facing is intermittent. Sometimes it works fine, but other times it acts up unexpectedly. | K92: Pending Customer Response | L92: Under Investigation | M92: High | N92: Phone | O92: 2023-06-01 07:15:41 | Q92: -1 | R92: High | S92: Pending Customer Response | T92: Login | U92: George Clark | V92: 44692.727 | Y92: 2022-05
A93: 92 | B93: Madeline Osborne | C93: tyler12@example.net | D93: 62 | E93: Male | F93: iPhone | G93: 2021-11-14 | H93: Product inquiry | I93: Display issue | J93: I'm having an issue with the {product_purchased}. Please assist. (Beware when I accidentally add a link to your product and the item you selected incorrectly, you may see some data about missing items and it may require This problem started occurring after the recent software update. I haven't made any other changes to the device. | K93: Pending Customer Response | L93: Under Investigation | M93: Low | N93: Email | O93: 2023-06-01 00:14:43 | Q93: -1 | R93: Low | S93: Pending Customer Response | T93: Technical | U93: Ethan Hunt | V93: 45342.774 | Y93: 2024-02
A94: 93 | B94: Sydney Wagner | C94: paul73@example.com | D94: 44 | E94: Male | F94: Bose QuietComfort | G94: 2021-05-27 | H94: Technical issue | I94: Peripheral compatibility | J94: I'm having an issue with the {product_purchased}. Please assist. Here are some additional notes about using the product in order to purchase the product: The "new" name of the product is used. This name I've noticed a sudden decrease in battery life on my {product_purchased}. It used to last much longer. | K94: Pending Customer Response | L94: Under Investigation | M94: Low | N94: Email | O94: 2023-06-01 15:57:45 | Q94: -1 | R94: Low | S94: Pending Customer Response | T94: Technical | U94: Hannah Abbott | V94: 45394.83 | Y94: 2024-04
A95: 94 | B95: Jeremy Good | C95: michael25@example.net | D95: 32 | E95: Female | F95: PlayStation | G95: 2021-05-24 | H95: Refund request | I95: Installation support | J95: I'm having an issue with the {product_purchased}. Please assist. In-app purchases don't always match up with your new product. In-app purchases are very costly. Make sure you also check if your product is I've noticed a peculiar error message popping up on my {product_purchased} screen. It says '{error_message}'. What does it mean? | K95: Open | L95: Under Investigation | M95: Low | N95: Email | Q95: -1 | R95: Low | S95: Open | T95: Technical | U95: Kevin Bacon | V95: 45176.369 | Y95: 2023-09
A96: 95 | B96: Scott Estrada | C96: davidcox@example.org | D96: 65 | E96: Other | F96: Microsoft Xbox Controller | G96: 2021-12-06 | H96: Product inquiry | I96: Account access | J96: I'm having an issue with the {product_purchased}. Please assist. </name> <product_purchased_url >http://www.kyle@junebug.com/tutorial/cure-all- I've tried troubleshooting steps mentioned in the user manual, but the issue persists. | K96: Open | L96: Under Investigation | M96: Critical | N96: Phone | Q96: -1 | R96: High | S96: Open | T96: Login | U96: Nancy Drew | V96: 45405.98 | Y96: 2024-04
A97: 96 | B97: Linda Campbell | C97: davisnatalie@example.net | D97: 60 | E97: Male | F97: Autodesk AutoCAD | G97: 2021-10-02 | H97: Product inquiry | I97: Battery life | J97: My {product_purchased} crashed, and I lost all the data stored on it. Is there any way to recover the lost data? Is there any way to recover the lost data? Can it be done remotely from a remote I've noticed a peculiar error message popping up on my {product_purchased} screen. It says '{error_message}'. What does it mean? | K97: Closed | L97: Series special into hour feel stuff. | M97: High | N97: Chat | O97: 2023-06-01 00:08:49 | P97: 2023-06-01 18:39:49 | Q97: 5 | R97: High | S97: Closed | T97: Technical | U97: Fiona Gallagher | V97: 45102.477 | W97: 2023-06-27 01:18:29.780842304 | X97: 37.86 | Y97: 2023-06
A98: 97 | B98: Charles Simpson | C98: vanessa39@example.net | D98: 18 | E98: Female | F98: Roomba Robot Vacuum | G98: 2020-10-25 | H98: Cancellation request | I98: Battery life | J98: I'm facing a problem with my {product_purchased}. The {product_purchased} is not turning on. It was working fine until yesterday, but now it doesn't respond. I'm thinking maybe they have a bug. I'm concerned about the security of my {product_purchased} and would like to ensure that my data is safe. | K98: Open | L98: Under Investigation | M98: High | N98: Social media | Q98: -1 | R98: High | S98: Open | T98: Technical | U98: Charlie Brown | V98: 45134.163 | Y98: 2023-07
A99: 98 | B99: Dan Newton | C99: deleonedward@example.net | D99: 22 | E99: Other | F99: Xbox | G99: 2020-01-18 | H99: Product inquiry | I99: Delivery problem | J99: I've recently set up my {product_purchased}, but it fails to connect to any available networks. What steps should I take to troubleshoot this issue? Step 1: You need to make sure that the DNS query you I've reviewed the troubleshooting steps on the official support website, but they didn't resolve the problem. | K99: Pending Customer Response | L99: Under Investigation | M99: High | N99: Email | O99: 2023-06-01 01:55:51 | Q99: -1 | R99: High | S99: Pending Customer Response | T99: Shipping | U99: Fiona Gallagher | V99: 45029.928 | Y99: 2023-04
A100: 99 | B100: Nichole Huang | C100: sheryldawson@example.org | D100: 38 | E100: Male | F100: Samsung Galaxy | G100: 2020-09-09 | H100: Billing inquiry | I100: Refund request | J100: I'm having an issue with the {product_purchased}. Please assist. <s3> Please provide the product name, location and shipping address in the Product Overview. <s3> This message will be unread for 12 seconds. I've recently updated the firmware of my {product_purchased}, and the issue started happening afterward. Could it be related to the update? | K100: Closed | L100: Generation officer force test evening certain sign oil. | M100: High | N100: Chat | O100: 2023-06-01 07:05:53 | P100: 2023-06-01 14:45:53 | Q100: 5 | R100: High | S100: Closed | T100: Refund | U100: Fiona Gallagher | V100: 44589.605 | W100: 2022-02-02 07:58:28.743005276 | X100: 113.46 | Y100: 2022-01
...
